{
    "hide_parse": false,
    "table_parse": 
    {
        "active_ws": "Pinmux",
        "function": 
        {
            "rid": 2, 
            "pattern": ["Function \\d+"]
        },
        "pad_name": 
        {
            "rid": 4,
            "pattern": "Pad Name"
        },
        "ref_name": 
        {
            "rid": 4,
            "pattern": "Pad Cell Name"
        }
    },
    "function_group": 
    {
        "SDIO": 
        {
            "pattern": "(SDIO\\d*)_\\w+(?:\\(BS\\))*",
            "clock": ["\\w+_CLK(?:\\(BS\\))*"],
            "custom": 
            {
                "DATA_H": "SDIO\\d*_D(?:0|1)(?:\\(BS\\))*"
            }
        },
        "BMC":
        {
            "pattern": "^(BMC)_\\w+",
            "clock": ["\\w+_CLK"],
            "custom": {}
        }
    },
    "function_ignore":
    [
        "FUNC_\\w+"
    ]
}
